[
  {
    "id": "08d6ea40-8a2b-11e9-927b-9bf496835ba2",
    "content": [
      "    -- Add titlebars to normal clients and dialogs",
      "    { rule_any = {type = { \"normal\", \"dialog\" }",
      "      }, properties = { titlebars_enabled = false }",
      "    },"
    ],
    "regtype": "V",
    "path": "file:///home/kyle/.config/awesome/rc.lua\t325\t1",
    "filetype": "lua"
  },
  {
    "id": "0d8fd3e0-8a2a-11e9-bdc0-bd9e76d6864b",
    "content": [
      "#ed9acc"
    ],
    "regtype": "v",
    "path": "file:///home/kyle/.config/awesome/themes/skyfall/theme.lua\t187\t28",
    "filetype": "lua"
  },
  {
    "id": "0c2dd2e0-8a2a-11e9-bdc0-bd9e76d6864b",
    "content": [
      "\"#ed9acc"
    ],
    "regtype": "v",
    "path": "file:///home/kyle/.config/awesome/themes/skyfall/theme.lua\t187\t27",
    "filetype": "lua"
  },
  {
    "id": "48980230-8a27-11e9-bdc0-bd9e76d6864b",
    "content": [
      "cal -3"
    ],
    "regtype": "v",
    "path": "file:///home/kyle/.config/awesome/rc.lua\t134\t47",
    "filetype": "lua"
  },
  {
    "id": "dc2ad0c0-8a24-11e9-83ca-61b91c46a4e0",
    "content": [
      "    client.connect_signal(\"property::maximized\", no_round_corners)"
    ],
    "regtype": "V",
    "path": "file:///home/kyle/.config/awesome/rc.lua\t407\t1",
    "filetype": "lua"
  },
  {
    "id": "cf6d8df0-8a24-11e9-83ca-61b91c46a4e0",
    "content": [
      "            c.shape = helpers.rect()"
    ],
    "regtype": "V",
    "path": "file:///home/kyle/.config/awesome/rc.lua\t400\t1",
    "filetype": "lua"
  },
  {
    "id": "e625b4b0-8a23-11e9-8042-910dd30e2322",
    "content": [
      "    callback = function (c)",
      "        if not beautiful.titlebars_imitate_borders then",
      "            awful.titlebar.hide(c)",
      "        end",
      "    end",
      "    },"
    ],
    "regtype": "V",
    "path": "file:///home/kyle/.config/awesome/rc.lua\t285\t1",
    "filetype": "lua"
  },
  {
    "id": "9cf86870-8a21-11e9-a935-230e500cb6a3",
    "content": [
      "compton --backend glx --blur-method kawase  --blur-background --blur-strength 12 --config ~/.config/compton/compton.conf -b"
    ],
    "regtype": "v",
    "path": "file:///home/kyle/.config/awesome/autorun.sh\t19\t5",
    "filetype": "sh"
  },
  {
    "id": "4cb2c950-8a21-11e9-b879-7fa4c631b95d",
    "content": [
      "opacity-rule = [",
      "      \"70:class_g = 'Spotify'\"",
      "];"
    ],
    "regtype": "V",
    "path": "file:///home/kyle/.config/compton/tmpcompton.conf\t134\t1",
    "filetype": "conf"
  },
  {
    "id": "57ff3380-8a20-11e9-bc19-ada970836736",
    "content": [
      "compton --backend glx --blur-method kawase  --blur-background --blur-strength 12 -b"
    ],
    "regtype": "v",
    "path": "file:///home/kyle/.config/awesome/autorun.sh\t19\t5",
    "filetype": "sh"
  },
  {
    "id": "cb1e3530-8a1d-11e9-9509-590eb79a03ef",
    "content": [
      " \"#ed9acc\""
    ],
    "regtype": "v",
    "path": "file:///home/kyle/.config/awesome/themes/skyfall/theme.lua\t187\t26",
    "filetype": "lua"
  },
  {
    "id": "efa54490-8a16-11e9-a969-034798c7ad2e",
    "content": [
      "run compton --backend glx --blur-method kawase  --blur-background --blur-strength 0 -b"
    ],
    "regtype": "V",
    "path": "file:///home/kyle/.config/awesome/autorun.sh\t19\t1",
    "filetype": "sh"
  },
  {
    "id": "ebbc98b0-8a16-11e9-a969-034798c7ad2e",
    "content": [
      "function run {",
      "        if [ -z $(pgrep $1) ]",
      "        then",
      "                $@",
      "        fi",
      "}"
    ],
    "regtype": "V",
    "path": "file:///home/kyle/.config/awesome/autorun.sh\t4\t1",
    "filetype": "sh"
  },
  {
    "id": "f8b96f50-88d3-11e9-b79a-d5df831312e3",
    "content": [
      "charger_unplugged"
    ],
    "regtype": "v",
    "path": "file:///home/kyle/.config/awesome/bar/battery.lua\t24\t34",
    "filetype": "lua"
  },
  {
    "id": "e87b1c10-88d3-11e9-b79a-d5df831312e3",
    "content": [
      "            awesome.emit_signal(\"charger_unplugged\")"
    ],
    "regtype": "V",
    "path": "file:///home/kyle/.config/awesome/bar/battery.lua\t27\t1",
    "filetype": "lua"
  },
  {
    "id": "c94fd4c0-88d3-11e9-b79a-d5df831312e3",
    "content": [
      "            awesome.emit_signal(\"charger_plugged\")"
    ],
    "regtype": "V",
    "path": "file:///home/kyle/.config/awesome/bar/battery.lua\t21\t1",
    "filetype": "lua"
  },
  {
    "id": "c4a0f2b0-88d3-11e9-b79a-d5df831312e3",
    "content": [
      "            awesome.emit_signal(\"charger_plugged\")"
    ],
    "regtype": "V",
    "path": "file:///home/kyle/.config/awesome/bar/battery.lua\t21\t1",
    "filetype": "lua"
  },
  {
    "id": "03b55ea0-88ca-11e9-a587-e3f69809ab88",
    "content": [
      "            awful.titlebar.hide(client.focus)"
    ],
    "regtype": "V",
    "path": "file:///home/kyle/.config/awesome/keys.lua\t81\t1",
    "filetype": "lua"
  },
  {
    "id": "0d4e89a0-88c0-11e9-8caa-b9e6c9f08ab4",
    "content": [
      "                    local tag = client.focus.screen.tags[i]"
    ],
    "regtype": "V",
    "path": "file:///home/kyle/.config/awesome/keys.lua\t296\t1",
    "filetype": "lua"
  },
  {
    "id": "5b086a40-88bf-11e9-8caa-b9e6c9f08ab4",
    "content": [
      "十"
    ],
    "regtype": "v",
    "path": "file:///home/kyle/.config/awesome/keys.lua\t81\t35",
    "filetype": "lua"
  },
  {
    "id": "56732ab0-88bf-11e9-8caa-b9e6c9f08ab4",
    "content": [
      "十"
    ],
    "regtype": "v",
    "path": "file:///home/kyle/.config/awesome/rc.lua\t193\t81",
    "filetype": "lua"
  },
  {
    "id": "7e4f97e0-88be-11e9-b35a-1334349c32d0",
    "content": [
      "            awful.titlebar.hide(c)"
    ],
    "regtype": "V",
    "path": "file:///home/kyle/.config/awesome/rc.lua\t295\t1",
    "filetype": "lua"
  },
  {
    "id": "fdbd2a20-88bd-11e9-b35a-1334349c32d0",
    "content": [
      "            awful.titlebar.hide(c)"
    ],
    "regtype": "V",
    "path": "file:///home/kyle/.config/awesome/rc.lua\t295\t1",
    "filetype": "lua"
  },
  {
    "id": "71755e90-88bb-11e9-b35a-1334349c32d0",
    "content": [
      "十"
    ],
    "regtype": "v",
    "path": "file:///home/kyle/.config/awesome/rc.lua\t193\t81",
    "filetype": "lua"
  },
  {
    "id": "611d1ab0-88bb-11e9-b35a-1334349c32d0",
    "content": [
      "    { rule_any = {",
      "        class = {",
      "            -- \"qutebrowser\",",
      "            --\"discord\",",
      "            --\"TelegramDesktop\",",
      "            \"Firefox\",",
      "            \"Spotify\",",
      "            \"kitty\",",
      "            \"Zathura\",",
      "            \"Steam\",",
      "            \"Chromium\",",
      "            \"Thunderbird\",",
      "        },",
      "    }, properties = {},",
      "    callback = function (c)",
      "        if not beautiful.titlebars_imitate_borders then",
      "            awful.titlebar.hide(c)",
      "        end",
      "    end",
      "    },"
    ],
    "regtype": "V",
    "path": "file:///home/kyle/.config/awesome/rc.lua\t276\t1",
    "filetype": "lua"
  },
  {
    "id": "2c9190f0-88bb-11e9-b35a-1334349c32d0",
    "content": [
      "四"
    ],
    "regtype": "v",
    "path": "file:///home/kyle/.config/awesome/rc.lua\t193\t39",
    "filetype": "lua"
  },
  {
    "id": "fa3458e0-88ba-11e9-b35a-1334349c32d0",
    "content": [
      "十"
    ],
    "regtype": "v",
    "path": "file:///home/kyle/.config/awesome/rc.lua\t193\t81",
    "filetype": "lua"
  },
  {
    "id": "eb7d8570-88b9-11e9-93ab-3fe437fa66e3",
    "content": [
      "    properties = { tag = \"三\" } },"
    ],
    "regtype": "V",
    "path": "file:///home/kyle/.config/awesome/rc.lua\t258\t1",
    "filetype": "lua"
  },
  {
    "id": "cdc926b0-88b9-11e9-93ab-3fe437fa66e3",
    "content": [
      "三"
    ],
    "regtype": "v",
    "path": "file:///home/kyle/.config/awesome/rc.lua\t193\t32",
    "filetype": "lua"
  },
  {
    "id": "7101c720-88b9-11e9-93ab-3fe437fa66e3",
    "content": [
      "三"
    ],
    "regtype": "v",
    "path": "file:///home/kyle/.config/awesome/rc.lua\t193\t32",
    "filetype": "lua"
  },
  {
    "id": "dc76e120-88b4-11e9-933c-35e7e54f84c7",
    "content": [
      "十"
    ],
    "regtype": "v",
    "path": "file:///home/kyle/.config/awesome/rc.lua\t193\t81",
    "filetype": "lua"
  },
  {
    "id": "778bc1e0-88a5-11e9-b124-37b14d3b84c3",
    "content": [
      " \"#abfeff\""
    ],
    "regtype": "v",
    "path": "file:///home/kyle/.config/awesome/sidebar.lua\t512\t35",
    "filetype": "lua"
  },
  {
    "id": "652cd890-88a5-11e9-b124-37b14d3b84c3",
    "content": [
      " \"#546577\""
    ],
    "regtype": "v",
    "path": "file:///home/kyle/.config/awesome/sidebar.lua\t515\t35",
    "filetype": "lua"
  },
  {
    "id": "36bde720-88a4-11e9-b124-37b14d3b84c3",
    "content": [
      "abfeff"
    ],
    "regtype": "v",
    "path": "file:///home/kyle/.config/awesome/sidebar.lua\t512\t38",
    "filetype": "lua"
  },
  {
    "id": "0a873d00-88a4-11e9-a5b4-3b37536db6d0",
    "content": [
      "  awful.spawn.easy_async({\"sh\", \"-c\", \"pactl list sinks\"},"
    ],
    "regtype": "V",
    "path": "file:///home/kyle/dotfiles_git/config/awesome/noodle/volume_bar.lua\t38\t1",
    "filetype": "lua"
  },
  {
    "id": "051224c0-88a4-11e9-a5b4-3b37536db6d0",
    "content": [
      "  awful.spawn.easy_async({\"sh\", \"-c\", \"pactl list sinks\"},"
    ],
    "regtype": "V",
    "path": "file:///home/kyle/dotfiles_git/config/awesome/noodle/volume_bar.lua\t38\t1",
    "filetype": "lua"
  },
  {
    "id": "fa53e640-88a3-11e9-a5b4-3b37536db6d0",
    "content": [
      "local function update_widget()",
      "  awful.spawn.easy_async({\"sh\", \"-c\", \"pactl list sinks\"},",
      "    function(stdout)",
      "      local volume = stdout:match('(%d+)%% /')",
      "      local muted = stdout:match('Mute:(%s+)[yes]')",
      "      local fill_color",
      "      local bg_color",
      "      if muted ~= nil then",
      "        fill_color = muted_color",
      "        bg_color = muted_background_color",
      "      else",
      "        fill_color = active_color",
      "        bg_color = active_background_color",
      "      end",
      "      volume_bar.value = tonumber(volume)",
      "      volume_bar.color = fill_color",
      "      volume_bar.background_color = bg_color",
      "    end",
      "  )",
      "end"
    ],
    "regtype": "V",
    "path": "file:///home/kyle/dotfiles_git/config/awesome/noodle/volume_bar.lua\t37\t1",
    "filetype": "lua"
  },
  {
    "id": "b6425cc0-88a3-11e9-a5b4-3b37536db6d0",
    "content": [
      "local function update_widget()",
      "  awful.spawn.easy_async({\"sh\", \"-c\", \"pactl list sinks\"},",
      "    function(stdout)",
      "      local volume = stdout:match('(%d+)%% /')",
      "      local muted = stdout:match('Mute:(%s+)[yes]')",
      "      local fill_color",
      "      local bg_color",
      "      if muted ~= nil then",
      "        fill_color = muted_color",
      "        bg_color = muted_background_color",
      "      else",
      "        fill_color = active_color",
      "        bg_color = active_background_color",
      "      end",
      "      volume_bar.value = tonumber(volume)",
      "      volume_bar.color = fill_color",
      "      volume_bar.background_color = bg_color",
      "    end",
      "  )",
      "end"
    ],
    "regtype": "V",
    "path": "file:///home/kyle/dotfiles_git/config/awesome/noodle/volume_bar.lua\t37\t1",
    "filetype": "lua"
  },
  {
    "id": "947eb750-88a3-11e9-b124-37b14d3b84c3",
    "content": [
      "abfeff"
    ],
    "regtype": "v",
    "path": "file:///home/kyle/.config/awesome/noodle/volume_bar.lua\t60\t36",
    "filetype": "lua"
  },
  {
    "id": "8e8aab10-88a3-11e9-b124-37b14d3b84c3",
    "content": [
      "546577"
    ],
    "regtype": "v",
    "path": "file:///home/kyle/.config/awesome/noodle/volume_bar.lua\t52\t36",
    "filetype": "lua"
  },
  {
    "id": "399f78b0-88a3-11e9-b124-37b14d3b84c3",
    "content": [
      "546577"
    ],
    "regtype": "v",
    "path": "file:///home/kyle/.config/awesome/noodle/volume_bar.lua\t53\t36",
    "filetype": "lua"
  },
  {
    "id": "2c2352b0-88a3-11e9-b124-37b14d3b84c3",
    "content": [
      "465463"
    ],
    "regtype": "v",
    "path": "file:///home/kyle/.config/awesome/themes/skyfall/theme.lua\t43\t24",
    "filetype": "lua"
  },
  {
    "id": "16ac2ce0-88a3-11e9-b124-37b14d3b84c3",
    "content": [
      "666666"
    ],
    "regtype": "v",
    "path": "file:///home/kyle/.config/awesome/noodle/volume_bar.lua\t15\t59",
    "filetype": "lua"
  },
  {
    "id": "0acc9fe0-88a3-11e9-b124-37b14d3b84c3",
    "content": [
      "#abfeff"
    ],
    "regtype": "v",
    "path": "file:///home/kyle/.config/awesome/noodle/volume_bar.lua\t61\t35",
    "filetype": "lua"
  },
  {
    "id": "fe238150-88a2-11e9-b124-37b14d3b84c3",
    "content": [
      "546577"
    ],
    "regtype": "v",
    "path": "file:///home/kyle/.config/awesome/noodle/volume_bar.lua\t53\t36",
    "filetype": "lua"
  },
  {
    "id": "4ec9fa90-88a2-11e9-b124-37b14d3b84c3",
    "content": [
      "noodle.volume_bar"
    ],
    "regtype": "v",
    "path": "file:///home/kyle/.config/awesome/keys.lua\t149\t28",
    "filetype": "lua"
  },
  {
    "id": "01d550a0-88a1-11e9-9088-19754f98778a",
    "content": [
      "ps aux | grep \"pactl subscribe\" | grep -v grep | awk '{print $2}' "
    ],
    "regtype": "v",
    "path": "file:///home/kyle/dotfiles_git/config/awesome/awesome-cleanup.sh\t13\t1",
    "filetype": "sh"
  },
  {
    "id": "dc7d0830-889f-11e9-b94f-470a392309c1",
    "content": [
      "  pactl subscribe 2> /dev/null | grep --line-buffered \"sink #0\""
    ],
    "regtype": "V",
    "path": "file:///home/kyle/dotfiles_git/config/awesome/noodle/volume_bar.lua\t63\t1",
    "filetype": "lua"
  },
  {
    "id": "cf48e7b0-889f-11e9-b94f-470a392309c1",
    "content": [
      "pactl list sinks"
    ],
    "regtype": "v",
    "path": "file:///home/kyle/dotfiles_git/config/awesome/noodle/volume_bar.lua\t38\t40",
    "filetype": "lua"
  },
  {
    "id": "936c0ba0-889f-11e9-b94f-470a392309c1",
    "content": [
      "      local muted = stdout:match('Mute:(%s+)[yes]')"
    ],
    "regtype": "V",
    "path": "file:///home/kyle/dotfiles_git/config/awesome/noodle/volume_bar.lua\t41\t1",
    "filetype": "lua"
  },
  {
    "id": "06cefeb0-889e-11e9-8274-b165d9d4b499",
    "content": [
      "                    if sidebar.ontop then",
      "                        sidebar.visible = false",
      "                        sidebar.ontop = false",
      "                    else",
      "                        sidebar.visible = true",
      "                        sidebar.ontop = true",
      "                    end"
    ],
    "regtype": "V",
    "path": "file:///home/kyle/.config/awesome/sidebar.lua\t576\t1",
    "filetype": "lua"
  },
  {
    "id": "f5cb98a0-889b-11e9-abeb-c7d49c32f37a",
    "content": [
      "pactl list sinks"
    ],
    "regtype": "v",
    "path": "file:///home/kyle/.config/awesome/noodle/volume_bar.lua\t43\t42",
    "filetype": "lua"
  },
  {
    "id": "c5bfe720-889a-11e9-abeb-c7d49c32f37a",
    "content": [
      "546577"
    ],
    "regtype": "v",
    "path": "file:///home/kyle/.config/awesome/sidebar.lua\t515\t38",
    "filetype": "lua"
  },
  {
    "id": "c2b58d50-889a-11e9-abeb-c7d49c32f37a",
    "content": [
      "#abfeff"
    ],
    "regtype": "v",
    "path": "file:///home/kyle/.config/awesome/noodle/volume_bar.lua\t60\t34",
    "filetype": "lua"
  },
  {
    "id": "bc31eb40-889a-11e9-abeb-c7d49c32f37a",
    "content": [
      "#abfeff"
    ],
    "regtype": "v",
    "path": "file:///home/kyle/.config/awesome/sidebar.lua\t512\t37",
    "filetype": "lua"
  },
  {
    "id": "fe89d350-8899-11e9-abeb-c7d49c32f37a",
    "content": [
      "abfeff"
    ],
    "regtype": "v",
    "path": "file:///home/kyle/.config/awesome/noodle/volume_bar.lua\t52\t34",
    "filetype": "lua"
  },
  {
    "id": "f0a6d530-8899-11e9-abeb-c7d49c32f37a",
    "content": [
      "abfeff"
    ],
    "regtype": "v",
    "path": "file:///home/kyle/.config/awesome/sidebar.lua\t512\t38",
    "filetype": "lua"
  },
  {
    "id": "a212ddb0-8899-11e9-abeb-c7d49c32f37a",
    "content": [
      "546577"
    ],
    "regtype": "v",
    "path": "file:///home/kyle/.config/awesome/sidebar.lua\t515\t38",
    "filetype": "lua"
  },
  {
    "id": "9b960bb0-8894-11e9-8112-554b150949ad",
    "content": [
      "        naughty.destroy(lock_not)"
    ],
    "regtype": "V",
    "path": "file:///home/kyle/.config/awesome/keys.lua\t156\t1",
    "filetype": "lua"
  },
  {
    "id": "4440bb50-888d-11e9-af80-577ef4a5d695",
    "content": [
      "            search_icon.image = beautiful.search_hover_icon"
    ],
    "regtype": "V",
    "path": "file:///home/kyle/.config/awesome/sidebar.lua\t483\t1",
    "filetype": "lua"
  },
  {
    "id": "2a08d920-888d-11e9-af80-577ef4a5d695",
    "content": [
      "            disk_icon.image = beautiful.files_hover_icon"
    ],
    "regtype": "V",
    "path": "file:///home/kyle/.config/awesome/sidebar.lua\t454\t1",
    "filetype": "lua"
  },
  {
    "id": "0bbe2dd0-888d-11e9-af80-577ef4a5d695",
    "content": [
      "    exit_icon = beautiful.poweroff_hover_icon"
    ],
    "regtype": "V",
    "path": "file:///home/kyle/.config/awesome/sidebar.lua\t39\t1",
    "filetype": "lua"
  },
  {
    "id": "7ebb64c0-888c-11e9-af80-577ef4a5d695",
    "content": [
      "theme.poweroff_icon = icon_path .. \"poweroff.png\""
    ],
    "regtype": "V",
    "path": "file:///home/kyle/.config/awesome/themes/skyfall/theme.lua\t276\t1",
    "filetype": "lua"
  },
  {
    "id": "7964f810-888c-11e9-af80-577ef4a5d695",
    "content": [
      "theme.files_icon = icon_path .. \"files.png\""
    ],
    "regtype": "V",
    "path": "file:///home/kyle/.config/awesome/themes/skyfall/theme.lua\t238\t1",
    "filetype": "lua"
  },
  {
    "id": "74a4d7f0-888c-11e9-af80-577ef4a5d695",
    "content": [
      "theme.poweroff_icon = icon_path .. \"poweroff.png\""
    ],
    "regtype": "V",
    "path": "file:///home/kyle/.config/awesome/themes/skyfall/theme.lua\t275\t1",
    "filetype": "lua"
  },
  {
    "id": "1a2322a0-888c-11e9-af80-577ef4a5d695",
    "content": [
      "theme.search_icon = icon_path .. \"search.png\""
    ],
    "regtype": "V",
    "path": "file:///home/kyle/.config/awesome/themes/skyfall/theme.lua\t226\t1",
    "filetype": "lua"
  },
  {
    "id": "d80c8a50-8881-11e9-af80-577ef4a5d695",
    "content": [
      "        -- change button color on hover",
      "        playerctl_prev_icon:connect_signal(\"mouse::enter\", function()",
      "            playerctl_prev_icon.image = beautiful.playerctl_prev_icon_hover",
      "        end)",
      "        playerctl_prev_icon:connect_signal(\"mouse::leave\", function()",
      "            playerctl_prev_icon.image = beautiful.playerctl_prev_icon",
      "        end)"
    ],
    "regtype": "V",
    "path": "file:///home/kyle/.config/awesome/sidebar.lua\t337\t1",
    "filetype": "lua"
  },
  {
    "id": "a0470b40-8881-11e9-af80-577ef4a5d695",
    "content": [
      "        -- change button color on hover",
      "        playerctl_toggle_icon:connect_signal(\"mouse::enter\", function()",
      "            playerctl_toggle_icon.image = beautiful.playerctl_toggle_icon_hover",
      "        end)",
      "        playerctl_toggle_icon:connect_signal(\"mouse::leave\", function()",
      "            playerctl_toggle_icon.image = beautiful.playerctl_toggle_icon",
      "        end)"
    ],
    "regtype": "V",
    "path": "file:///home/kyle/.config/awesome/sidebar.lua\t316\t1",
    "filetype": "lua"
  },
  {
    "id": "5585c6a0-8881-11e9-af80-577ef4a5d695",
    "content": [
      "        -- change text color on hover",
      "        -- time:connect_signal(\"mouse::enter\", function()",
      "        --     time.markup = helpers.colorize_text(time.text, \"#c9bff7\")",
      "        -- end)",
      "        -- time:connect_signal(\"mouse::leave\", function()",
      "        --     time.markup = helpers.colorize_text(time.text, \"#F1FCF9\")",
      "        -- end)",
      ""
    ],
    "regtype": "V",
    "path": "file:///home/kyle/.config/awesome/sidebar.lua\t365\t1",
    "filetype": "lua"
  },
  {
    "id": "04ed2580-8881-11e9-af80-577ef4a5d695",
    "content": [
      "theme.playerctl_toggle_icon = icon_path .. \"playerctl_toggle.png\"",
      "theme.playerctl_prev_icon = icon_path .. \"playerctl_prev.png\"",
      "theme.playerctl_next_icon = icon_path .. \"playerctl_next.png\""
    ],
    "regtype": "V",
    "path": "file:///home/kyle/.config/awesome/themes/skyfall/theme.lua\t219\t1",
    "filetype": "lua"
  },
  {
    "id": "44ea9c70-8878-11e9-bd3b-d511b2be8fef",
    "content": [
      " \"#abfeff\""
    ],
    "regtype": "v",
    "path": "file:///home/kyle/.config/awesome/noodle/volume_bar.lua\t60\t33",
    "filetype": "lua"
  },
  {
    "id": "225f8850-8878-11e9-bd3b-d511b2be8fef",
    "content": [
      "\"#546577\" "
    ],
    "regtype": "v",
    "path": "file:///home/kyle/.config/awesome/noodle/volume_bar.lua\t52\t34",
    "filetype": "lua"
  },
  {
    "id": "f0c85f60-8877-11e9-bd3b-d511b2be8fef",
    "content": [
      " \"#abfeff\""
    ],
    "regtype": "v",
    "path": "file:///home/kyle/.config/awesome/sidebar.lua\t491\t27",
    "filetype": "lua"
  },
  {
    "id": "83bd7c70-8877-11e9-bd3b-d511b2be8fef",
    "content": [
      "local function update_widget()",
      "    awful.spawn.easy_async({\"sh\", \"-c\", \"pactl list sinks\"},",
      "        function(stdout)",
      "            local volume = stdout:match('(%d+)%% /')",
      "            local muted = stdout:match('Mute:(%s+)[yes]')",
      "            local fill_color",
      "            local bg_color",
      "            if muted ~= nil then",
      "                is_muted = true",
      "                if hover then",
      "                    fill_color = \"#546577\" ",
      "                else",
      "                    fill_color = muted_color",
      "                end",
      "                bg_color = muted_background_color",
      "            else",
      "                is_muted = false",
      "                fill_color = active_color",
      "                bg_color = active_background_color",
      "            end",
      "            volume_bar.value = tonumber(volume)",
      "            volume_bar.color = fill_color",
      "            volume_bar.background_color = bg_color",
      "        end",
      "  )",
      "end"
    ],
    "regtype": "V",
    "path": "file:///home/kyle/.config/awesome/noodle/volume_bar.lua\t40\t1",
    "filetype": "lua"
  },
  {
    "id": "60699a10-8877-11e9-bd3b-d511b2be8fef",
    "content": [
      " \"#546577\""
    ],
    "regtype": "v",
    "path": "file:///home/kyle/.config/awesome/sidebar.lua\t494\t27",
    "filetype": "lua"
  },
  {
    "id": "3063bf80-8877-11e9-bd3b-d511b2be8fef",
    "content": [
      "        volume_bar.hover(true)"
    ],
    "regtype": "V",
    "path": "file:///home/kyle/.config/awesome/sidebar.lua\t492\t1",
    "filetype": "lua"
  },
  {
    "id": "795060a0-8876-11e9-bd3b-d511b2be8fef",
    "content": [
      "546577"
    ],
    "regtype": "v",
    "path": "file:///home/kyle/.config/awesome/sidebar.lua\t493\t30",
    "filetype": "lua"
  },
  {
    "id": "4e369830-8876-11e9-bd3b-d511b2be8fef",
    "content": [
      "abfeff"
    ],
    "regtype": "v",
    "path": "file:///home/kyle/.config/awesome/sidebar.lua\t491\t30",
    "filetype": "lua"
  },
  {
    "id": "4c38f370-8876-11e9-bd3b-d511b2be8fef",
    "content": [
      "465463"
    ],
    "regtype": "v",
    "path": "file:///home/kyle/.config/awesome/sidebar.lua\t508\t43",
    "filetype": "lua"
  },
  {
    "id": "4a7857b0-8876-11e9-bd3b-d511b2be8fef",
    "content": [
      "abfeff"
    ],
    "regtype": "v",
    "path": "file:///home/kyle/.config/awesome/sidebar.lua\t491\t30",
    "filetype": "lua"
  },
  {
    "id": "307233e0-8876-11e9-bd3b-d511b2be8fef",
    "content": [
      " \"#546577\""
    ],
    "regtype": "v",
    "path": "file:///home/kyle/.config/awesome/sidebar.lua\t493\t27",
    "filetype": "lua"
  },
  {
    "id": "454bfdb0-8875-11e9-98cc-4d68d488a7fe",
    "content": [
      "acpi | awk '{ print $3 $4 }'"
    ],
    "regtype": "v",
    "path": "file:///home/kyle/.config/awesome/bar/battery.lua\t11\t21",
    "filetype": "lua"
  },
  {
    "id": "1cf481d0-882e-11e9-8bb3-73330d4fbbc2",
    "content": [
      "7ef7a0"
    ],
    "regtype": "v",
    "path": "file:///home/kyle/.config/awesome/noodle/text_exit_screen.lua\t119\t68",
    "filetype": "lua"
  },
  {
    "id": "fb45eb00-882d-11e9-8bb3-73330d4fbbc2",
    "content": [
      "DB86BA"
    ],
    "regtype": "v",
    "path": "file:///home/kyle/.config/awesome/noodle/text_exit_screen.lua\t84\t72",
    "filetype": "lua"
  },
  {
    "id": "ebe91e20-882d-11e9-8bb3-73330d4fbbc2",
    "content": [
      "74DD91"
    ],
    "regtype": "v",
    "path": "file:///home/kyle/.config/awesome/noodle/text_exit_screen.lua\t122\t68",
    "filetype": "lua"
  },
  {
    "id": "d8bbe850-882d-11e9-8bb3-73330d4fbbc2",
    "content": [
      "B4A1DB"
    ],
    "regtype": "v",
    "path": "file:///home/kyle/.config/awesome/noodle/text_exit_screen.lua\t237\t64",
    "filetype": "lua"
  },
  {
    "id": "d5723b90-882d-11e9-8bb3-73330d4fbbc2",
    "content": [
      "B4A1DB"
    ],
    "regtype": "v",
    "path": "file:///home/kyle/.config/awesome/noodle/text_exit_screen.lua\t204\t60",
    "filetype": "lua"
  },
  {
    "id": "bd809fe0-882d-11e9-8bb3-73330d4fbbc2",
    "content": [
      "-- highlight during hover",
      "exit:connect_signal(\"mouse::enter\", function()",
      "    exit_icon.markup = helpers.colorize_text(exit_icon.text, \"#83f8ff\")",
      "end)",
      "exit:connect_signal(\"mouse::leave\", function()",
      "    exit_icon.markup = helpers.colorize_text(exit_icon.text, \"#75DBE1\")",
      "end)",
      ""
    ],
    "regtype": "V",
    "path": "file:///home/kyle/.config/awesome/noodle/text_exit_screen.lua\t194\t1",
    "filetype": "lua"
  },
  {
    "id": "af707740-882d-11e9-8bb3-73330d4fbbc2",
    "content": [
      "E49186"
    ],
    "regtype": "v",
    "path": "file:///home/kyle/.config/awesome/noodle/text_exit_screen.lua\t160\t70",
    "filetype": "lua"
  },
  {
    "id": "a2dd2aa0-882d-11e9-8bb3-73330d4fbbc2",
    "content": [
      "E49186"
    ],
    "regtype": "v",
    "path": "file:///home/kyle/.config/awesome/noodle/text_exit_screen.lua\t160\t70",
    "filetype": "lua"
  },
  {
    "id": "a18821f0-882d-11e9-8bb3-73330d4fbbc2",
    "content": [
      "fa9b8f"
    ],
    "regtype": "v",
    "path": "file:///home/kyle/.config/awesome/noodle/text_exit_screen.lua\t157\t70",
    "filetype": "lua"
  },
  {
    "id": "7e5b9db0-882d-11e9-8bb3-73330d4fbbc2",
    "content": [
      "75DBE1"
    ],
    "regtype": "v",
    "path": "file:///home/kyle/.config/awesome/noodle/text_exit_screen.lua\t199\t64",
    "filetype": "lua"
  },
  {
    "id": "7b61bea0-882d-11e9-8bb3-73330d4fbbc2",
    "content": [
      "75DBE1"
    ],
    "regtype": "v",
    "path": "file:///home/kyle/.config/awesome/noodle/text_exit_screen.lua\t166\t60",
    "filetype": "lua"
  },
  {
    "id": "68a80b20-882d-11e9-8bb3-73330d4fbbc2",
    "content": [
      "-- highlight during hover",
      "suspend:connect_signal(\"mouse::enter\", function()",
      "    suspend_icon.markup = helpers.colorize_text(suspend_icon.text, \"#fa9b8f\")",
      "end)",
      "suspend:connect_signal(\"mouse::leave\", function()",
      "    suspend_icon.markup = helpers.colorize_text(suspend_icon.text, \"#E49186\")",
      "end)",
      ""
    ],
    "regtype": "V",
    "path": "file:///home/kyle/.config/awesome/noodle/text_exit_screen.lua\t155\t1",
    "filetype": "lua"
  },
  {
    "id": "4e65c8b0-882d-11e9-8bb3-73330d4fbbc2",
    "content": [
      "E49186"
    ],
    "regtype": "v",
    "path": "file:///home/kyle/.config/awesome/noodle/text_exit_screen.lua\t127\t66",
    "filetype": "lua"
  },
  {
    "id": "39fd05a0-882d-11e9-8bb3-73330d4fbbc2",
    "content": [
      "E49186"
    ],
    "regtype": "v",
    "path": "file:///home/kyle/.config/awesome/noodle/text_exit_screen.lua\t127\t66",
    "filetype": "lua"
  },
  {
    "id": "24b1aac0-882d-11e9-8bb3-73330d4fbbc2",
    "content": [
      "",
      "-- highlight during hover",
      "reboot:connect_signal(\"mouse::enter\", function()",
      "    reboot_icon.markup = helpers.colorize_text(reboot_icon.text, \"#83f4a2\")",
      "end)",
      "reboot:connect_signal(\"mouse::leave\", function()",
      "    reboot_icon.markup = helpers.colorize_text(reboot_icon.text, \"#74DD91\")",
      "end)"
    ],
    "regtype": "V",
    "path": "file:///home/kyle/.config/awesome/noodle/text_exit_screen.lua\t116\t1",
    "filetype": "lua"
  },
  {
    "id": "10746480-882d-11e9-8bb3-73330d4fbbc2",
    "content": [
      "74DD91"
    ],
    "regtype": "v",
    "path": "file:///home/kyle/.config/awesome/noodle/text_exit_screen.lua\t122\t68",
    "filetype": "lua"
  },
  {
    "id": "0ad8d880-882d-11e9-8bb3-73330d4fbbc2",
    "content": [
      "74DD91"
    ],
    "regtype": "v",
    "path": "file:///home/kyle/.config/awesome/noodle/text_exit_screen.lua\t89\t64",
    "filetype": "lua"
  },
  {
    "id": "f1d99d60-882c-11e9-8bb3-73330d4fbbc2",
    "content": [
      "-- highlight during hover",
      "poweroff:connect_signal(\"mouse::enter\", function()",
      "    poweroff_icon.markup = helpers.colorize_text(poweroff_icon.text, \"#f99bd4\")",
      "end)",
      "poweroff:connect_signal(\"mouse::leave\", function()",
      "    poweroff_icon.markup = helpers.colorize_text(poweroff_icon.text, \"#DB86BA\")",
      "end)"
    ],
    "regtype": "V",
    "path": "file:///home/kyle/.config/awesome/noodle/text_exit_screen.lua\t79\t1",
    "filetype": "lua"
  },
  {
    "id": "e270e9a0-882c-11e9-8bb3-73330d4fbbc2",
    "content": [
      "DB86BA"
    ],
    "regtype": "v",
    "path": "file:///home/kyle/.config/awesome/noodle/text_exit_screen.lua\t84\t72",
    "filetype": "lua"
  },
  {
    "id": "c257e6f0-882c-11e9-8bb3-73330d4fbbc2",
    "content": [
      "DB86BA"
    ],
    "regtype": "v",
    "path": "file:///home/kyle/.config/awesome/noodle/text_exit_screen.lua\t84\t72",
    "filetype": "lua"
  },
  {
    "id": "bb024ee0-882c-11e9-8bb3-73330d4fbbc2",
    "content": [
      "DB86BA"
    ],
    "regtype": "v",
    "path": "file:///home/kyle/.config/awesome/noodle/text_exit_screen.lua\t51\t68",
    "filetype": "lua"
  },
  {
    "id": "8bf5ef80-882c-11e9-8bb3-73330d4fbbc2",
    "content": [
      "-- change text color on hover",
      "time:connect_signal(\"mouse::enter\", function()",
      "    time.markup = helpers.colorize_text(time.text, \"#c9bff7\")",
      "end)",
      "time:connect_signal(\"mouse::leave\", function()",
      "    time.markup = helpers.colorize_text(time.text, \"#F1FCF9\")",
      "end)"
    ],
    "regtype": "V",
    "path": "file:///home/kyle/.config/awesome/sidebar.lua\t365\t1",
    "filetype": "lua"
  },
  {
    "id": "6275a840-882b-11e9-a6c6-9bc23e1f0caa",
    "content": [
      "    mpd_title.markup = helpers.colorize_text(mpd_title.text, \"#c9bff7\")"
    ],
    "regtype": "V",
    "path": "file:///home/kyle/.config/awesome/sidebar.lua\t298\t1",
    "filetype": "lua"
  },
  {
    "id": "61628a90-882b-11e9-a6c6-9bc23e1f0caa",
    "content": [
      "    mpd_title.markup = helpers.colorize_text(mpd_title.text, \"#F1FCF9\")"
    ],
    "regtype": "V",
    "path": "file:///home/kyle/.config/awesome/sidebar.lua\t301\t1",
    "filetype": "lua"
  },
  {
    "id": "466d99f0-882b-11e9-a6c6-9bc23e1f0caa",
    "content": [
      "-- change text color on hover",
      "exit:connect_signal(\"mouse::enter\", function()",
      "    exit_text.markup = helpers.colorize_text(exit_text.text, \"#c9bff7\")",
      "end)",
      "exit:connect_signal(\"mouse::leave\", function()",
      "    exit_text.markup = helpers.colorize_text(exit_text.text, \"#F1FCF9\")",
      "end)"
    ],
    "regtype": "V",
    "path": "file:///home/kyle/.config/awesome/sidebar.lua\t37\t1",
    "filetype": "lua"
  },
  {
    "id": "dfafb8b0-882a-11e9-a6c6-9bc23e1f0caa",
    "content": [
      "",
      "-- change text color on hover",
      "search:connect_signal(\"mouse::enter\", function()",
      "    search_text.markup = helpers.colorize_text(search_text.text, \"#c9bff7\")",
      "end)",
      "search:connect_signal(\"mouse::leave\", function()",
      "    search_text.markup = helpers.colorize_text(disk_spacesearch_texttext, \"#F1FCF9\")",
      "end)"
    ],
    "regtype": "V",
    "path": "file:///home/kyle/.config/awesome/sidebar.lua\t451\t1",
    "filetype": "lua"
  },
  {
    "id": "cc47c3d0-882a-11e9-a6c6-9bc23e1f0caa",
    "content": [
      "",
      "-- change text color on hover",
      "disk:connect_signal(\"mouse::enter\", function()",
      "    disk_space.markup = helpers.colorize_text(disk_space.text, \"#c9bff7\")",
      "end)",
      "disk:connect_signal(\"mouse::leave\", function()",
      "    disk_space.markup = helpers.colorize_text(disk_space.text, \"#F1FCF9\")",
      "end)"
    ],
    "regtype": "V",
    "path": "file:///home/kyle/.config/awesome/sidebar.lua\t422\t1",
    "filetype": "lua"
  },
  {
    "id": "9e7f7d30-882a-11e9-a6c6-9bc23e1f0caa",
    "content": [
      "-- change text color on hover",
      "fancy_date:connect_signal(\"mouse::enter\", function()",
      "    fancy_date.markup = helpers.colorize_text(fancy_date.text, \"#c9bff7\")",
      "end)",
      "fancy_date:connect_signal(\"mouse::leave\", function()",
      "    fancy_date.markup = helpers.colorize_text(fancy_date.text, \"#F1FCF9\")",
      "end)"
    ],
    "regtype": "V",
    "path": "file:///home/kyle/.config/awesome/sidebar.lua\t386\t1",
    "filetype": "lua"
  },
  {
    "id": "7f4541c0-882a-11e9-a6c6-9bc23e1f0caa",
    "content": [
      "-- change text color on hover",
      "date:connect_signal(\"mouse::enter\", function()",
      "    date.markup = helpers.colorize_text(date.text, \"#c9bff7\")",
      "end)",
      "date:connect_signal(\"mouse::leave\", function()",
      "    date.markup = helpers.colorize_text(date.text, \"#F1FCF9\")",
      "end)",
      ""
    ],
    "regtype": "V",
    "path": "file:///home/kyle/.config/awesome/sidebar.lua\t372\t1",
    "filetype": "lua"
  },
  {
    "id": "6a54b110-882a-11e9-a6c6-9bc23e1f0caa",
    "content": [
      "-- change text color on hover",
      "time:connect_signal(\"mouse::enter\", function()",
      "    time.markup = helpers.colorize_text(time.text, \"#c9bff7\")",
      "end)",
      "time:connect_signal(\"mouse::leave\", function()",
      "    time.markup = helpers.colorize_text(time.text, \"#F1FCF9\")",
      "end)"
    ],
    "regtype": "V",
    "path": "file:///home/kyle/.config/awesome/sidebar.lua\t357\t1",
    "filetype": "lua"
  },
  {
    "id": "d09679f0-8829-11e9-a6c6-9bc23e1f0caa",
    "content": [
      "F1FCF9"
    ],
    "regtype": "v",
    "path": "file:///home/kyle/.config/awesome/themes/skyfall/theme.lua\t34\t24",
    "filetype": "lua"
  },
  {
    "id": "ac371b00-8829-11e9-a6c6-9bc23e1f0caa",
    "content": [
      "EEFFFF"
    ],
    "regtype": "v",
    "path": "file:///home/kyle/.config/awesome/themes/manta/theme.lua\t34\t42",
    "filetype": "lua"
  },
  {
    "id": "9c7571d0-8829-11e9-a6c6-9bc23e1f0caa",
    "content": [
      "    time.markup = helpers.colorize_text(time.text, \"#75DBE1\")"
    ],
    "regtype": "V",
    "path": "file:///home/kyle/.config/awesome/sidebar.lua\t358\t1",
    "filetype": "lua"
  },
  {
    "id": "8cb2de40-8829-11e9-a6c6-9bc23e1f0caa",
    "content": [
      "exit_icon.markup = helpers.colorize_text(exit_icon.text, \"#75DBE1\")"
    ],
    "regtype": "V",
    "path": "file:///home/kyle/.config/awesome/noodle/text_exit_screen.lua\t142\t1",
    "filetype": "lua"
  },
  {
    "id": "850eff20-8829-11e9-a6c6-9bc23e1f0caa",
    "content": [
      "time.connect_signal(\"mouse_enter\", function()",
      "    ",
      "end)"
    ],
    "regtype": "V",
    "path": "file:///home/kyle/.config/awesome/sidebar.lua\t357\t1",
    "filetype": "lua"
  },
  {
    "id": "f6b734c0-8825-11e9-9275-5158337f001d",
    "content": [
      "44ced6"
    ],
    "regtype": "v",
    "path": "file:///home/kyle/.config/awesome/sidebar.lua\t254\t23",
    "filetype": "lua"
  },
  {
    "id": "e4ab7480-8825-11e9-9275-5158337f001d",
    "content": [
      "6be0e0"
    ],
    "regtype": "v",
    "path": "file:///home/kyle/.config/awesome/sidebar.lua\t122\t30",
    "filetype": "lua"
  },
  {
    "id": "ccb1e990-8825-11e9-9275-5158337f001d",
    "content": [
      "7fee9d"
    ],
    "regtype": "v",
    "path": "file:///home/kyle/.config/awesome/sidebar.lua\t207\t23",
    "filetype": "lua"
  },
  {
    "id": "ac09ed50-8825-11e9-9275-5158337f001d",
    "content": [
      "c0abea"
    ],
    "regtype": "v",
    "path": "file:///home/kyle/.config/awesome/sidebar.lua\t160\t27",
    "filetype": "lua"
  },
  {
    "id": "92e86250-8813-11e9-98b9-518e1031614b",
    "content": [
      "launcher = \"rofi -show drun\""
    ],
    "regtype": "V",
    "path": "file:///home/kyle/.config/awesome/rc.lua\t69\t1",
    "filetype": "lua"
  },
  {
    "id": "21c81e30-8813-11e9-baf1-8936e2da6cf9",
    "content": [
      "pgrep rofi"
    ],
    "regtype": "v",
    "path": "file:///home/kyle/.bin/rofi-toggle\t3\t11",
    "filetype": "sh"
  },
  {
    "id": "fee685a0-8812-11e9-98b9-518e1031614b",
    "content": [
      "rofi -show drun"
    ],
    "regtype": "v",
    "path": "file:///home/kyle/.config/awesome/rc.lua\t69\t13",
    "filetype": "lua"
  },
  {
    "id": "be707260-8812-11e9-a5d6-ff21f654c498",
    "content": [
      "if [ -z $(pgrep xss-lock) ]",
      "then",
      "\txss-lock -l fade-lock +resetsaver &",
      "\tnotify-send \"Auto-Lock On\"",
      "else",
      "\tkillall xss-lock",
      "\tnotify-send \"Auto-Lock Off\"",
      "fi"
    ],
    "regtype": "V",
    "path": "file:///home/kyle/.bin/lock-toggle\t3\t1",
    "filetype": "sh"
  },
  {
    "id": "cd072590-8811-11e9-9856-0931ba3adc7c",
    "content": [
      "%d+%%"
    ],
    "regtype": "v",
    "path": "file:///home/kyle/.config/awesome/bar/battery.lua\t16\t49",
    "filetype": "lua"
  },
  {
    "id": "a2d4d6f0-8811-11e9-9856-0931ba3adc7c",
    "content": [
      "acpi | awk '{ print $3 $4 }'"
    ],
    "regtype": "v",
    "path": "file:///home/kyle/.config/awesome/bar/battery.lua\t11\t21",
    "filetype": "lua"
  },
  {
    "id": "5f3369d0-8810-11e9-9856-0931ba3adc7c",
    "content": [
      "        brightness_bar:connect_signal(\"brightness_changed\", _)"
    ],
    "regtype": "V",
    "path": "file:///home/kyle/.config/awesome/keys.lua\t135\t1",
    "filetype": "lua"
  },
  {
    "id": "88f523b0-880d-11e9-95ab-f354f95d4913",
    "content": [
      "%B %d"
    ],
    "regtype": "v",
    "path": "file:///home/kyle/.config/awesome/sidebar.lua\t374\t47",
    "filetype": "lua"
  },
  {
    "id": "94194560-880c-11e9-95ab-f354f95d4913",
    "content": [
      "exit:connect_signal(\"mouse::enter\", function ()",
      "    exit_text.markup = \"<span foreground='#e2cdff'>Exit</span>\"",
      "end)",
      "exit:connect_signal(\"mouse::leave\", function ()",
      "    exit_text.markup = \"<span foreground='#f1fcf9'>Exit</span>\"",
      "end)"
    ],
    "regtype": "V",
    "path": "file:///home/kyle/.config/awesome/sidebar.lua\t38\t1",
    "filetype": "lua"
  },
  {
    "id": "2f1a2b20-880c-11e9-95ab-f354f95d4913",
    "content": [
      "ed9acc"
    ],
    "regtype": "v",
    "path": "file:///home/kyle/.config/awesome/themes/skyfall/theme.lua\t187\t29",
    "filetype": "lua"
  },
  {
    "id": "2b8fcbe0-880c-11e9-95ab-f354f95d4913",
    "content": [
      "e2cdff"
    ],
    "regtype": "v",
    "path": "file:///home/kyle/.config/awesome/sidebar.lua\t39\t44",
    "filetype": "lua"
  },
  {
    "id": "240456c0-880c-11e9-95ab-f354f95d4913",
    "content": [
      "ed9acc"
    ],
    "regtype": "v",
    "path": "file:///home/kyle/.config/awesome/themes/skyfall/theme.lua\t187\t29",
    "filetype": "lua"
  },
  {
    "id": "98f917f0-880b-11e9-95ab-f354f95d4913",
    "content": [
      "e2cdff"
    ],
    "regtype": "v",
    "path": "file:///home/kyle/.config/awesome/sidebar.lua\t39\t44",
    "filetype": "lua"
  },
  {
    "id": "761eab50-880b-11e9-95ab-f354f95d4913",
    "content": [
      "e2cdff"
    ],
    "regtype": "v",
    "path": "file:///home/kyle/.config/awesome/sidebar.lua\t438\t46",
    "filetype": "lua"
  },
  {
    "id": "460dad30-880b-11e9-95ab-f354f95d4913",
    "content": [
      "-- lighten exit text when hovering",
      "exit:connect_signal(\"mouse::enter\", function ()",
      "    exit_text.markup = \"<span foreground='#dbc1ff'>Exit</span>\"",
      "end)",
      "exit:connect_signal(\"mouse::leave\", function ()",
      "    exit_text.markup = \"<span foreground='#f1fcf9'>Exit</span>\"",
      "end)"
    ],
    "regtype": "V",
    "path": "file:///home/kyle/.config/awesome/sidebar.lua\t37\t1",
    "filetype": "lua"
  },
  {
    "id": "228ec330-880b-11e9-95ab-f354f95d4913",
    "content": [
      "dbc1ff"
    ],
    "regtype": "v",
    "path": "file:///home/kyle/.config/awesome/sidebar.lua\t374\t39",
    "filetype": "lua"
  },
  {
    "id": "73f0eb50-880a-11e9-95ab-f354f95d4913",
    "content": [
      "c1dcff"
    ],
    "regtype": "v",
    "path": "file:///home/kyle/.config/awesome/sidebar.lua\t374\t39",
    "filetype": "lua"
  },
  {
    "id": "17214e60-880a-11e9-95ab-f354f95d4913",
    "content": [
      "-- lighten exit text when hovering",
      "exit:connect_signal(\"mouse::enter\", function ()",
      "    exit_text.markup = \"<span foreground='#ffffff'>Exit</span>\"",
      "end)",
      "exit:connect_signal(\"mouse::leave\", function ()",
      "    exit_text.markup = \"<span foreground='#f1fcf9'>Exit</span>\"",
      "end)"
    ],
    "regtype": "V",
    "path": "file:///home/kyle/.config/awesome/sidebar.lua\t37\t1",
    "filetype": "lua"
  },
  {
    "id": "b944fc60-8809-11e9-95ab-f354f95d4913",
    "content": [
      "    exit_text.markup = \"<span foreground=\"blue\">Exit</span>\""
    ],
    "regtype": "V",
    "path": "file:///home/kyle/.config/awesome/sidebar.lua\t39\t1",
    "filetype": "lua"
  },
  {
    "id": "413a6520-8809-11e9-95ab-f354f95d4913",
    "content": [
      "F1FCF9"
    ],
    "regtype": "v",
    "path": "file:///home/kyle/.config/awesome/themes/skyfall/theme.lua\t34\t24",
    "filetype": "lua"
  },
  {
    "id": "dda53b20-8808-11e9-95ab-f354f95d4913",
    "content": [
      "-- lighten battery color when hovering",
      "battery:connect_signal(\"mouse::enter\", function ()",
      "    battery_bar.color = \"#c0abea\"",
      "end)",
      "battery:connect_signal(\"mouse::leave\", function ()",
      "    battery_bar.color = \"#B4A1DB\"",
      "end)",
      ""
    ],
    "regtype": "V",
    "path": "file:///home/kyle/.config/awesome/sidebar.lua\t158\t1",
    "filetype": "lua"
  },
  {
    "id": "a7fb2200-8808-11e9-95ab-f354f95d4913",
    "content": [
      "B4A1DB"
    ],
    "regtype": "v",
    "path": "file:///home/kyle/.config/awesome/sidebar.lua\t163\t27",
    "filetype": "lua"
  },
  {
    "id": "a158fb70-8808-11e9-95ab-f354f95d4913",
    "content": [
      "  \"#B4A1DB\""
    ],
    "regtype": "v",
    "path": "file:///home/kyle/.config/awesome/themes/skyfall/theme.lua\t40\t20",
    "filetype": "lua"
  },
  {
    "id": "85912a70-8808-11e9-95ab-f354f95d4913",
    "content": [
      "-- lighten ram color when hovering",
      "ram:connect_signal(\"mouse::enter\", function ()",
      "    ram_bar.color = \"#44ced6\"",
      "end)",
      "ram:connect_signal(\"mouse::leave\", function ()",
      "    ram_bar.color = \"#3DBAC2\"",
      "end)"
    ],
    "regtype": "V",
    "path": "file:///home/kyle/.config/awesome/sidebar.lua\t244\t1",
    "filetype": "lua"
  },
  {
    "id": "6534b620-8808-11e9-95ab-f354f95d4913",
    "content": [
      "#3DBAC2"
    ],
    "regtype": "v",
    "path": "file:///home/kyle/.config/awesome/sidebar.lua\t249\t29",
    "filetype": "lua"
  },
  {
    "id": "63b54210-8808-11e9-95ab-f354f95d4913",
    "content": [
      " \"#3DBAC2\""
    ],
    "regtype": "v",
    "path": "file:///home/kyle/.config/awesome/sidebar.lua\t249\t27",
    "filetype": "lua"
  },
  {
    "id": "5c7b4850-8808-11e9-95ab-f354f95d4913",
    "content": [
      "  \"#3DBAC2\""
    ],
    "regtype": "v",
    "path": "file:///home/kyle/.config/awesome/themes/skyfall/theme.lua\t47\t20",
    "filetype": "lua"
  },
  {
    "id": "4b79a510-8808-11e9-95ab-f354f95d4913",
    "content": [
      "-- lighten brightness color when hovering",
      "brightness:connect_signal(\"mouse::enter\", function ()",
      "    brightness_bar.color = \"#6be0e0\"",
      "end)",
      "brightness:connect_signal(\"mouse::leave\", function ()",
      "    brightness_bar.color =  \"#62CDCD\"",
      "end)"
    ],
    "regtype": "V",
    "path": "file:///home/kyle/.config/awesome/sidebar.lua\t120\t1",
    "filetype": "lua"
  },
  {
    "id": "29de2110-8808-11e9-95ab-f354f95d4913",
    "content": [
      "#62CDCD"
    ],
    "regtype": "v",
    "path": "file:///home/kyle/.config/awesome/sidebar.lua\t125\t23",
    "filetype": "lua"
  },
  {
    "id": "228de030-8808-11e9-95ab-f354f95d4913",
    "content": [
      "  \"#62CDCD\""
    ],
    "regtype": "v",
    "path": "file:///home/kyle/.config/awesome/themes/skyfall/theme.lua\t49\t20",
    "filetype": "lua"
  },
  {
    "id": "0577e450-8808-11e9-95ab-f354f95d4913",
    "content": [
      "-- lighten cpu color when hovering",
      "cpu:connect_signal(\"mouse::enter\", function ()",
      "    cpu_bar.color = \"#7fee9d\"",
      "end)",
      "cpu:connect_signal(\"mouse::leave\", function ()",
      "    cpu_bar.color =  \"#74DD91\"",
      "end)"
    ],
    "regtype": "V",
    "path": "file:///home/kyle/.config/awesome/sidebar.lua\t189\t1",
    "filetype": "lua"
  },
  {
    "id": "ec60db70-8807-11e9-95ab-f354f95d4913",
    "content": [
      "74DD91"
    ],
    "regtype": "v",
    "path": "file:///home/kyle/.config/awesome/sidebar.lua\t194\t24",
    "filetype": "lua"
  },
  {
    "id": "e7f236b0-8807-11e9-95ab-f354f95d4913",
    "content": [
      "  \"#74DD91\""
    ],
    "regtype": "v",
    "path": "file:///home/kyle/.config/awesome/themes/skyfall/theme.lua\t37\t20",
    "filetype": "lua"
  },
  {
    "id": "9022f730-8807-11e9-95ab-f354f95d4913",
    "content": [
      "-- lighten color when hovering",
      "volume:connect_signal(\"mouse::enter\", function ()",
      "    if (not volume_bar.muted()) then",
      "        volume_bar.color = \"#abfeff\"",
      "    else",
      "        volume_bar.color = \"#546577\"",
      "    end",
      "end)",
      "volume:connect_signal(\"mouse::leave\", function ()",
      "    if (not volume_bar.muted()) then",
      "        volume_bar.color = beautiful.xcolor6",
      "    else",
      "        volume_bar.color = \"#465463\"",
      "    end",
      "end)"
    ],
    "regtype": "V",
    "path": "file:///home/kyle/.config/awesome/sidebar.lua\t408\t1",
    "filetype": "lua"
  },
  {
    "id": "660edef0-8807-11e9-95ab-f354f95d4913",
    "content": [
      "        volume_bar.color = \"#465463\""
    ],
    "regtype": "V",
    "path": "file:///home/kyle/.config/awesome/sidebar.lua\t420\t1",
    "filetype": "lua"
  },
  {
    "id": "7e52fce0-8806-11e9-95ab-f354f95d4913",
    "content": [
      " \"#465463\""
    ],
    "regtype": "v",
    "path": "file:///home/kyle/.config/awesome/tmp\t3\t31",
    "filetype": ""
  },
  {
    "id": "69637da0-8806-11e9-95ab-f354f95d4913",
    "content": [
      " \"#abfeff\""
    ],
    "regtype": "v",
    "path": "file:///home/kyle/.config/awesome/sidebar.lua\t411\t27",
    "filetype": "lua"
  },
  {
    "id": "32fbe0e0-8806-11e9-95ab-f354f95d4913",
    "content": [
      "    awful.key({}, \"XF86AudioPlay\",       function ()",
      "        awful.spawn.with_shell(\"dbus-send --print-reply --dest=org.mpris.MediaPlayer2.spotify /org/mpris/MediaPlayer2 org.mpris.MediaPlayer2.Player.PlayPause\")",
      "    end, {description = \"play or pause spotify\", group = \"launcher\"}),"
    ],
    "regtype": "V",
    "path": "file:///home/kyle/.config/awesome/keys.lua\t108\t1",
    "filetype": "lua"
  },
  {
    "id": "bf51e4a0-8805-11e9-95ab-f354f95d4913",
    "content": [
      "        volume_bar.color = \"#abfeff\""
    ],
    "regtype": "V",
    "path": "file:///home/kyle/.config/awesome/sidebar.lua\t411\t1",
    "filetype": "lua"
  },
  {
    "id": "b61934b0-8805-11e9-95ab-f354f95d4913",
    "content": [
      "#465463"
    ],
    "regtype": "v",
    "path": "file:///home/kyle/.config/awesome/tmp\t3\t33",
    "filetype": ""
  },
  {
    "id": "8ae22040-8805-11e9-95ab-f354f95d4913",
    "content": [
      "\"#465463\""
    ],
    "regtype": "v",
    "path": "file:///home/kyle/.config/awesome/tmp\t3\t32",
    "filetype": ""
  },
  {
    "id": "5a8d8970-8805-11e9-95ab-f354f95d4913",
    "content": [
      "9EE9EA"
    ],
    "regtype": "v",
    "path": "file:///home/kyle/.config/awesome/sidebar.lua\t413\t63",
    "filetype": "lua"
  },
  {
    "id": "49bc9320-8805-11e9-95ab-f354f95d4913",
    "content": [
      "9EE9EA"
    ],
    "regtype": "v",
    "path": "file:///home/kyle/.config/awesome/sidebar.lua\t413\t63",
    "filetype": "lua"
  },
  {
    "id": "3fdbbc50-8805-11e9-95ab-f354f95d4913",
    "content": [
      "9EE9EA"
    ],
    "regtype": "v",
    "path": "file:///home/kyle/.config/awesome/tmp\t2\t47",
    "filetype": ""
  },
  {
    "id": "20513e00-8805-11e9-95ab-f354f95d4913",
    "content": [
      "#9EE9EA"
    ],
    "regtype": "v",
    "path": "file:///home/kyle/.config/awesome/tmp\t1\t34",
    "filetype": ""
  },
  {
    "id": "177728d0-8805-11e9-95ab-f354f95d4913",
    "content": [
      " \"#9EE9EA\""
    ],
    "regtype": "v",
    "path": "file:///home/kyle/.config/awesome/tmp\t1\t32",
    "filetype": ""
  },
  {
    "id": "13813680-8805-11e9-95ab-f354f95d4913",
    "content": [
      " \"#465463\""
    ],
    "regtype": "v",
    "path": "file:///home/kyle/.config/awesome/tmp\t3\t31",
    "filetype": ""
  },
  {
    "id": "120ff340-8805-11e9-95ab-f354f95d4913",
    "content": [
      "#465463"
    ],
    "regtype": "v",
    "path": "file:///home/kyle/.config/awesome/tmp\t3\t32",
    "filetype": ""
  },
  {
    "id": "0d0b2900-8805-11e9-95ab-f354f95d4913",
    "content": [
      "#465463"
    ],
    "regtype": "v",
    "path": "file:///home/kyle/.config/awesome/themes/skyfall/theme.lua\t43\t23",
    "filetype": "lua"
  },
  {
    "id": "09bd3680-8805-11e9-95ab-f354f95d4913",
    "content": [
      "#9EE9EA"
    ],
    "regtype": "v",
    "path": "file:///home/kyle/.config/awesome/tmp\t1\t33",
    "filetype": ""
  },
  {
    "id": "046c9630-8805-11e9-95ab-f354f95d4913",
    "content": [
      "#9EE9EA"
    ],
    "regtype": "v",
    "path": "file:///home/kyle/.config/awesome/themes/skyfall/theme.lua\t41\t23",
    "filetype": "lua"
  },
  {
    "id": "f9b890e0-8804-11e9-95ab-f354f95d4913",
    "content": [
      "theme.volume_bar_active_color = theme.xcolor6",
      "theme.volume_bar_active_background_color = theme.xcolor6 .. \"33\"",
      "theme.volume_bar_muted_color = theme.xcolor8",
      "theme.volume_bar_muted_background_color = theme.xcolor8 .. \"33\""
    ],
    "regtype": "V",
    "path": "file:///home/kyle/.config/awesome/themes/skyfall/theme.lua\t431\t1",
    "filetype": "lua"
  },
  {
    "id": "57fff630-8804-11e9-a01f-6728c247fad3",
    "content": [
      "awful.spawn.with_shell(\"~/.config/awesome/awesome-cleanup.sh\")"
    ],
    "regtype": "V",
    "path": "file:///home/kyle/dotfiles_git/config/awesome/rc.lua\t63\t1",
    "filetype": "lua"
  },
  {
    "id": "3b3a3d30-8804-11e9-a01f-6728c247fad3",
    "content": [
      "#!/bin/bash",
      "# Noodle Cleanup Script",
      "#   Some of my widgets (mpd, volume) rely on scripts that have to be",
      "#   run persistently in the background.",
      "#   They sleep until mpd/volume state changes, in an infinite loop.",
      "#   As a result when awesome restarts, they keep running in background, along with the new ones that are created after the restart.",
      "#   This script cleans up the old processes.",
      "",
      "# Mpd widget",
      "ps aux | grep \"mpc idleloop player\" | grep -v grep | awk '{print $2}' | xargs kill",
      "#ps aux | grep \"mpc idle player\" | grep -v grep | awk '{print $2}' | xargs kill",
      "# Volume widget",
      "ps aux | grep \"pactl subscribe\" | grep -v grep | awk '{print $2}' | xargs kill"
    ],
    "regtype": "V",
    "path": "file:///home/kyle/dotfiles_git/config/awesome/awesome-cleanup.sh\t1\t1",
    "filetype": "sh"
  },
  {
    "id": "afcc9310-8803-11e9-a9d3-bb356f31d22d",
    "content": [
      "pactl subscribe 2> /dev/null | grep --line-buffered \"sink #0\""
    ],
    "regtype": "v",
    "path": "file:///home/kyle/.config/awesome/noodle/volume_bar.lua\t63\t3",
    "filetype": "lua"
  },
  {
    "id": "c19aa380-8802-11e9-b7d8-bd96281c7273",
    "content": [
      "function run {",
      "        if [ -z $(pgrep $1) ]",
      "        then",
      "                echo run",
      "                $@",
      "        else",
      "                echo no",
      "        fi",
      "}"
    ],
    "regtype": "V",
    "path": "file:///home/kyle/.config/awesome/autorun.sh\t4\t1",
    "filetype": "sh"
  },
  {
    "id": "65950d50-8802-11e9-b7d8-bd96281c7273",
    "content": [
      "function run {",
      "        if ! pgrep $1 > /dev/null ;",
      "        then",
      "                echo hello",
      "                $@&",
      "        else",
      "                echo no",
      "        fi",
      "}"
    ],
    "regtype": "V",
    "path": "file:///home/kyle/.config/awesome/autorun.sh\t4\t1",
    "filetype": "sh"
  },
  {
    "id": "3f7057b0-8802-11e9-b7d8-bd96281c7273",
    "content": [
      "function run {",
      "        if ! pgrep $1 > /dev/null ;",
      "        then",
      "                $@&",
      "        fi",
      "}"
    ],
    "regtype": "V",
    "path": "file:///home/kyle/.config/awesome/autorun.sh\t4\t1",
    "filetype": "sh"
  },
  {
    "id": "07469890-8802-11e9-b7d8-bd96281c7273",
    "content": [
      "amixer set Master unmute"
    ],
    "regtype": "V",
    "path": "file:///home/kyle/.config/awesome/autorun.sh\t12\t1",
    "filetype": "sh"
  },
  {
    "id": "182c92f0-8801-11e9-800d-25f70aa8b04a",
    "content": [
      "5AA3CC"
    ],
    "regtype": "v",
    "path": "file:///home/kyle/.config/awesome/noodle/volume_bar.lua\t14\t61",
    "filetype": "lua"
  },
  {
    "id": "07ed5550-8801-11e9-800d-25f70aa8b04a",
    "content": [
      "89c5e7"
    ],
    "regtype": "v",
    "path": "file:///home/kyle/.config/awesome/noodle/volume_bar.lua\t14\t61",
    "filetype": "lua"
  },
  {
    "id": "e7ef0690-8800-11e9-800d-25f70aa8b04a",
    "content": [
      "5AA3CC"
    ],
    "regtype": "v",
    "path": "file:///home/kyle/.config/awesome/noodle/volume_bar.lua\t14\t61",
    "filetype": "lua"
  },
  {
    "id": "d38dbd90-8800-11e9-800d-25f70aa8b04a",
    "content": [
      "5AA3CC"
    ],
    "regtype": "v",
    "path": "file:///home/kyle/.config/awesome/noodle/volume_bar.lua\t14\t61",
    "filetype": "lua"
  },
  {
    "id": "aedcb1a0-87ff-11e9-800d-25f70aa8b04a",
    "content": [
      "beautiful.volume_bar_active_color or \"#5AA3CC\""
    ],
    "regtype": "v",
    "path": "file:///home/kyle/.config/awesome/noodle/volume_bar.lua\t14\t22",
    "filetype": "lua"
  },
  {
    "id": "a6797a20-87ff-11e9-800d-25f70aa8b04a",
    "content": [
      "volume_bar:connect_signal(\"mouse::enter\", function ()",
      "    volume_bar.active_color = \"#5facd8\"",
      "end)"
    ],
    "regtype": "V",
    "path": "file:///home/kyle/.config/awesome/sidebar.lua\t395\t1",
    "filetype": "lua"
  },
  {
    "id": "a3914e50-87ff-11e9-800d-25f70aa8b04a",
    "content": [
      "5facd8"
    ],
    "regtype": "v",
    "path": "file:///home/kyle/.config/awesome/sidebar.lua\t396\t31",
    "filetype": "lua"
  },
  {
    "id": "90102c20-87ff-11e9-800d-25f70aa8b04a",
    "content": [
      "\"mouse::enter\", function ()",
      "                                     sidebar.visible = true",
      "  end"
    ],
    "regtype": "v",
    "path": "file:///home/kyle/.config/awesome/sidebar.lua\t472\t36",
    "filetype": "lua"
  },
  {
    "id": "5222bf90-87ff-11e9-800d-25f70aa8b04a",
    "content": [
      "#5AA3CC"
    ],
    "regtype": "v",
    "path": "file:///home/kyle/.config/awesome/noodle/volume_bar.lua\t14\t60",
    "filetype": "lua"
  },
  {
    "id": "4f8172b0-87fd-11e9-8624-79afee4caac1",
    "content": [
      "            sidebar.visible = false"
    ],
    "regtype": "V",
    "path": "file:///home/kyle/.config/awesome/keys.lua\t177\t1",
    "filetype": "lua"
  },
  {
    "id": "e5eaac10-87f5-11e9-af3a-011e1482ddbc",
    "content": [
      "next song in spotify"
    ],
    "regtype": "v",
    "path": "file:///home/kyle/.config/awesome/keys.lua\t114\t26",
    "filetype": "lua"
  },
  {
    "id": "e09ccae0-87f5-11e9-af3a-011e1482ddbc",
    "content": [
      "previous song in spotify"
    ],
    "regtype": "v",
    "path": "file:///home/kyle/.config/awesome/keys.lua\t118\t26",
    "filetype": "lua"
  },
  {
    "id": "dc664d20-87f5-11e9-af3a-011e1482ddbc",
    "content": [
      "        awful.spawn.with_shell(\"dbus-send --print-reply --dest=org.mpris.MediaPlayer2.spotify /org/mpris/MediaPlayer2 org.mpris.MediaPlayer2.Player.Previous\")",
      "        mpd_song.update()"
    ],
    "regtype": "V",
    "path": "file:///home/kyle/.config/awesome/keys.lua\t116\t1",
    "filetype": "lua"
  },
  {
    "id": "c6a3c670-87f5-11e9-af3a-011e1482ddbc",
    "content": [
      "        awful.spawn.with_shell(\"dbus-send --print-reply --dest=org.mpris.MediaPlayer2.spotify /org/mpris/MediaPlayer2 org.mpris.MediaPlayer2.Player.Next\")",
      "        mpd_song.update()"
    ],
    "regtype": "V",
    "path": "file:///home/kyle/.config/awesome/keys.lua\t112\t1",
    "filetype": "lua"
  },
  {
    "id": "be376730-87f5-11e9-af3a-011e1482ddbc",
    "content": [
      "    -- awful.key({ modkey,           }, \"l\",     function () awful.tag.incmwfact( 0.05)          end,",
      "    --     {description = \"increase master width factor\", group = \"layout\"}),",
      "    -- awful.key({ modkey,           }, \"h\",     function () awful.tag.incmwfact(-0.05)          end,",
      "    --     {description = \"decrease master width factor\", group = \"layout\"}),"
    ],
    "regtype": "V",
    "path": "file:///home/kyle/.config/awesome/keys.lua\t179\t1",
    "filetype": "lua"
  },
  {
    "id": "298d6b00-87f2-11e9-a167-af82283e3afc",
    "content": [
      "dbus-send --print-reply --session --dest=org.mpris.MediaPlayer2.spotify /org/mpris/MediaPlayer2 org.freedesktop.DBus.Properties.Get string:'org.mpris.MediaPlayer2.Player' string:'Metadata' | grep -A 2 -e title -e artist | sed -n -e '3p' -e '6p'"
    ],
    "regtype": "v",
    "path": "file:///home/kyle/.config/awesome/noodle/mpd_song.lua\t37\t23",
    "filetype": "lua"
  },
  {
    "id": "a9a84680-87ec-11e9-85d9-611b616a48b1",
    "content": [
      "            artist = one:match('\"(.+)\"')"
    ],
    "regtype": "V",
    "path": "file:///home/kyle/.config/awesome/noodle/mpd_song.lua\t166\t1",
    "filetype": "lua"
  },
  {
    "id": "9c051080-87ec-11e9-85d9-611b616a48b1",
    "content": [
      "        local one = io.read(\"*line\")",
      "        local two = io.read(\"*line\")"
    ],
    "regtype": "V",
    "path": "file:///home/kyle/.config/awesome/bar/battery.lua\t17\t1",
    "filetype": "lua"
  },
  {
    "id": "95dd9830-87ec-11e9-85d9-611b616a48b1",
    "content": [
      "        local one = io.read(\"*line\")"
    ],
    "regtype": "V",
    "path": "file:///home/kyle/.config/awesome/bar/battery.lua\t17\t1",
    "filetype": "lua"
  },
  {
    "id": "c743d800-87ea-11e9-85d9-611b616a48b1",
    "content": [
      "  --       if (title == nil) then",
      "  --           mpd_title.text = \"---------\"",
      "  --       else",
      "  --           mpd_title.text = title"
    ],
    "regtype": "V",
    "path": "file:///home/kyle/.config/awesome/noodle/mpd_song.lua\t132\t1",
    "filetype": "lua"
  }
]